[
    {
        "subtype": "channel_join",
        "user": "U016EHMM2K0",
        "text": "<@U016EHMM2K0> has joined the channel",
        "type": "message",
        "ts": "1594065689.387400"
    },
    {
        "subtype": "channel_join",
        "user": "U016TGY3676",
        "text": "<@U016TGY3676> has joined the channel",
        "type": "message",
        "ts": "1594068099.387600"
    },
    {
        "user": "U016TGY3676",
        "type": "message",
        "ts": "1594072275.387900",
        "edited": {
            "user": "U016TGY3676",
            "ts": "1594072924.000000"
        },
        "client_msg_id": "82913e36-df3f-4cf5-a155-6f31ded61748",
        "text": "~Hi All,~\n~\"errorMessage\":\"AppKey is not configured for service\"~\n~Have been running bots for years but only just getting into streaming. Any ideas?~\nScratch that! I have a main account and a sub-account. Turns out that my main account is enabled for streaming but sub-account isn't.",
        "team": "T4G9NBD2M",
        "user_team": "T4G9NBD2M",
        "source_team": "T4G9NBD2M",
        "user_profile": {
            "avatar_hash": "g6a681220e11",
            "image_72": "https:\/\/secure.gravatar.com\/avatar\/6a681220e11c1a2ed3685375d658dadb.jpg?s=72&d=https%3A%2F%2Fa.slack-edge.com%2Fdf10d%2Fimg%2Favatars%2Fava_0001-72.png",
            "first_name": "",
            "real_name": "birchy",
            "display_name": "birchy",
            "team": "T4G9NBD2M",
            "name": "birchy",
            "is_restricted": false,
            "is_ultra_restricted": false
        },
        "blocks": [
            {
                "type": "rich_text",
                "block_id": "LGcc",
                "elements": [
                    {
                        "type": "rich_text_section",
                        "elements": [
                            {
                                "type": "text",
                                "text": "Hi All,",
                                "style": {
                                    "strike": true
                                }
                            },
                            {
                                "type": "text",
                                "text": "\n"
                            },
                            {
                                "type": "text",
                                "text": "\"errorMessage\":\"AppKey is not configured for service\"",
                                "style": {
                                    "strike": true
                                }
                            },
                            {
                                "type": "text",
                                "text": "\n"
                            },
                            {
                                "type": "text",
                                "text": "Have been running bots for years but only just getting into streaming. Any ideas?",
                                "style": {
                                    "strike": true
                                }
                            },
                            {
                                "type": "text",
                                "text": "\nScratch that! I have a main account and a sub-account. Turns out that my main account is enabled for streaming but sub-account isn't."
                            }
                        ]
                    }
                ]
            }
        ]
    },
    {
        "subtype": "channel_join",
        "user": "U016F7AQ5PG",
        "text": "<@U016F7AQ5PG> has joined the channel",
        "type": "message",
        "ts": "1594099434.388500"
    }
]